{
    "country": "England",
    "fullname": "Benjamin Robert William Stebbings",
    "birth_place": "Oxford, Oxfordshire, England",
    "batting": "Right-handed",
    "bowling": "Right-arm Right-arm medium",
    "source": "http://www.espncricinfo.com/ci/content/player/292842.html Cricinfo ",
    "First-class": {
        "matches": "4",
        "runs": "90",
        "bat avg": "6.00",
        "100s/50s": "&ndash;/&ndash;",
        "top score": "29",
        "deliveries": "&ndash;",
        "wickets": "&ndash;",
        "bowl avg": "&ndash;",
        "fivefor": "&ndash;",
        "tenfor": "&ndash;",
        "best bowling": "&ndash;",
        "catches/stumpings": "2/&ndash;"
    },
    "clubs": {
        "Oxford MCCU": "2010&ndash;2011",
        "Herefordshire": "2007&ndash;present"
    },
    "birth_date": "1989-10-4"
}