{
    "country": "England",
    "fullname": "David Thomas Smith",
    "birth_place": "Canterbury, Kent, England",
    "heightft": "6",
    "heightinch": "1",
    "batting": "Right-handed",
    "bowling": "Right-arm Right-arm medium",
    "source": "http://www.espncricinfo.com/england/content/player/399652.html Cricinfo ",
    "First-class": {
        "matches": "3",
        "runs": "36",
        "bat avg": "18.00",
        "100s/50s": "\u2013/\u2013",
        "deliveries": "75",
        "wickets": "1",
        "bowl avg": "64.00",
        "fivefor": "\u2013",
        "tenfor": "\u2013",
        "best bowling": "1/29",
        "catches/stumpings": "4/\u2013"
    },
    "clubs": {
        "Oxford UCCE/MCCU": "2009&ndash;2011",
        "Oxfordshire": "2009&ndash;2013"
    },
    "birth_date": "1989-9-13"
}