{
    "name": "Elijah Carrington",
    "country": "England",
    "fullname": "Elijah Carrington",
    "birth_place": "Blackwell, Derbyshire, England",
    "death_date": "1998",
    "death_place": "Hillcote, Derbyshire, England",
    "batting": "Right-handed",
    "type1": "FC",
    "debutdate1": "9 June",
    "debutyear1": "1934",
    "debutfor1": "Derbyshire",
    "debutagainst1": "Hampshire",
    "lastdate1": "23 June",
    "lastyear1": "1937",
    "lastfor1": "Derbyshire",
    "lastagainst1": "Hampshire",
    "source": "https://cricketarchive.com/Players/28/28436/28436.html CricketArchive ",
    "First-class": {
        "matches": "50",
        "runs": "1,470",
        "bat avg": "20.13",
        "100s/50s": "0/8",
        "top score": "80",
        "deliveries": "42",
        "wickets": "0",
        "bowl avg": "\u2013",
        "fivefor": "\u2013",
        "tenfor": "\u2013",
        "best bowling": "\u2013",
        "catches/stumpings": "18/\u2013"
    },
    "clubs": {
        "Derbyshire": "1934\u20131937"
    },
    "birth_date": "1914-3-25"
}