{
    "name": "Fanie de Villiers",
    "country": "South Africa",
    "fullname": "Petrus Stephanus de Villiers",
    "nickname": "Fanie",
    "heightft": "6",
    "heightinch": "2",
    "birth_place": "Vereeniging, Transvaal Province, South Africa",
    "batting": "Right-handed",
    "bowling": "Right arm Right arm fast-medium",
    "testdebutdate": "26 December",
    "testdebutyear": "1993",
    "testdebutagainst": "Australia",
    "testcap": "256",
    "lasttestdate": "10 March",
    "lasttestyear": "1998",
    "lasttestagainst": "Pakistan",
    "odidebutdate": "7 December",
    "odidebutyear": "1992",
    "odidebutagainst": "India",
    "odicap": "23",
    "lastodidate": "8 November",
    "lastodiyear": "1997",
    "lastodiagainst": "Sri Lanka",
    "source": "http://cricinfo.com/ci/content/player/44696.html Cricinfo ",
    "Test": {
        "matches": "18",
        "runs": "359",
        "bat avg": "18.89",
        "100s/50s": "0/2",
        "deliveries": "4,805",
        "wickets": "85",
        "bowl avg": "24.27",
        "fivefor": "5",
        "tenfor": "2",
        "best bowling": "6/23",
        "catches/stumpings": "11/\u2013"
    },
    "ODI": {
        "matches": "83",
        "runs": "170",
        "bat avg": "8.09",
        "100s/50s": "0/0",
        "deliveries": "4,422",
        "wickets": "95",
        "bowl avg": "27.74",
        "fivefor": "0",
        "tenfor": "0",
        "best bowling": "4/27",
        "catches/stumpings": "15/\u2013"
    },
    "FC": {
        "matches": "102",
        "runs": "1,687",
        "bat avg": "17.04",
        "100s/50s": "0/4",
        "top score": "68",
        "deliveries": "20,498",
        "wickets": "427",
        "bowl avg": "22.37",
        "fivefor": "23",
        "tenfor": "3",
        "best bowling": "7/80",
        "catches/stumpings": "53/\u2013"
    },
    "LA": {
        "matches": "173",
        "runs": "519",
        "bat avg": "9.26",
        "100s/50s": "0/0",
        "deliveries": "8,765",
        "wickets": "204",
        "bowl avg": "26.82",
        "fivefor": "1",
        "tenfor": "0",
        "best bowling": "5/30",
        "catches/stumpings": "24/\u2013"
    },
    "clubs": {
        "Northern Transvaal": "1985/86\u20131997/98",
        "Kent": "1990"
    },
    "birth_date": "1964-10-13"
}