{
    "country": "England",
    "fullname": "Frederick William Bosworth",
    "birth_place": "Westerham, Kent, England",
    "death_date": "df=yes",
    "death_place": "Pau, Basses-Pyr\u00e9n\u00e9es, France",
    "batting": "Unknown",
    "source": "http://www.espncricinfo.com/england/content/player/10486.html Cricinfo ",
    "First-class": {
        "matches": "1",
        "runs": "2",
        "bat avg": "1.00",
        "100s/50s": "\u2013/\u2013",
        "top score": "2",
        "catches/stumpings": "1/\u2013"
    },
    "clubs": {}
}