{
    "name": "Geoffrey Fletcher",
    "fullname": "Geoffrey Everingham Fletcher",
    "birth_place": "Charterhouse School, Godalming, Surrey, England",
    "death_date": "1943",
    "death_place": "Djebel Saikra, Mareth Line, Matmata, Tunisia",
    "batting": "Right-handed",
    "source": "https://cricketarchive.com/Archive/Players/3/3546/3546.html CricketArchive ",
    "FC": {
        "matches": "5",
        "runs": "165",
        "bat avg": "18.33",
        "100s/50s": "0/1",
        "top score": "65",
        "deliveries": "8",
        "wickets": "0",
        "bowl avg": "\u2013",
        "fivefor": "\u2013",
        "tenfor": "\u2013",
        "best bowling": "0/15",
        "catches/stumpings": "4/\u2013"
    },
    "clubs": {
        "Oxford University": "1939",
        "Somerset": "1939"
    },
    "birth_date": "1919-7-20"
}