{
    "name": "George Yates",
    "country": "England",
    "birth_place": "Bolsover, Derbyshire, England",
    "death_date": "1933",
    "death_place": "Bolsover, England",
    "batting": "Right-handed",
    "bowling": "Right-arm",
    "type1": "FC",
    "debutdate1": "9 July",
    "debutyear1": "1883",
    "debutfor1": "Derbyshire",
    "debutagainst1": "MCC",
    "onetype1": "true",
    "source": "https://cricketarchive.com/Players/34/34141/34141.html CricketArchive ",
    "First-class": {
        "matches": "1",
        "runs": "0",
        "bat avg": "0.00",
        "100s/50s": "0/0",
        "top score": "0",
        "deliveries": "12",
        "wickets": "0",
        "bowl avg": "\u2013",
        "fivefor": "\u2013",
        "tenfor": "\u2013",
        "best bowling": "\u2013",
        "catches/stumpings": "0/\u2013"
    },
    "clubs": {
        "Derbyshire": "1883"
    },
    "birth_date": "1858-8-21"
}