{
    "name": "George Arthur",
    "country": "Australia",
    "fullname": "George Henry Arthur",
    "birth_place": "Longford, Tasmania, Australia",
    "death_date": "1932",
    "death_place": "Longford, Tasmania, Australia",
    "family": "Charles Arthur (father), JLA Arthur (brother)",
    "type1": "First-class",
    "debutdate1": "12 February",
    "debutyear1": "1869",
    "debutfor1": "Tasmania",
    "debutagainst1": "Victoria",
    "lastdate1": "10 November",
    "lastyear1": "1877",
    "lastfor1": ", Tasmania",
    "lastagainst1": "South Australia",
    "source": "http://www.cricketarchive.co.uk/Archive/Players/2/2377/2377.html CricketArchive ",
    "First-class cricket": {
        "matches": "2",
        "runs": "33",
        "bat avg": "11.00",
        "100s/50s": "0/0",
        "top score": "26",
        "catches/stumpings": "0/&ndash;"
    },
    "clubs": {
        "Tasmania": "1869, 1877"
    },
    "birth_date": "1849-3-10"
}