{
    "name": "Ghulam Parkar",
    "full_name": "Ghulam Ahmed Hasan Mohammed Parkar",
    "birth_place": "Kalusta, Maharashtra, India",
    "batting": "Right-handed",
    "bowling": "Right-arm Right-arm medium",
    "onetest": "yes",
    "country": "India",
    "testcap": "157",
    "testdebutfor": "India",
    "testdebutagainst": "England",
    "testdebutdate": "10 June",
    "testdebutyear": "1982",
    "lasttestdate": "10 June",
    "lasttestyear": "1982",
    "lasttestfor": "India",
    "lasttestagainst": "England",
    "odicap": "41",
    "odidebutdate": "2 June",
    "odidebutyear": "1982",
    "odidebutagainst": "England",
    "lastodidate": "31 October",
    "lastodiyear": "1984",
    "lastodiagainst": "Pakistan",
    "source": "https://www.espncricinfo.com/india/content/player/32201.html CricInfo ",
    "Test": {
        "matches": "1",
        "runs": "7",
        "bat avg": "3.50",
        "100s/50s": "0/0",
        "top score": "6",
        "catches/stumpings": "1/\u2013"
    },
    "ODI": {
        "matches": "10",
        "runs": "165",
        "bat avg": "18.33",
        "100s/50s": "0/0",
        "top score": "42",
        "catches/stumpings": "4/\u2013"
    },
    "clubs": {},
    "birth_date": "1955-10-25"
}