{
    "name": "Hasan Dar",
    "fullname": "Hasan Ahmed Dar",
    "birth_place": "Lahore, Pakistan",
    "batting": "Right-handed",
    "bowling": "Right-arm Right-arm medium-fast",
    "source": "https://cricketarchive.com/Players/191/191967/191967.html CricketArchive",
    "module": "Infobox medal templates",
    "titlestyle": "background-color: lightsteelblue;",
    "expand": "yes",
    "clubs": {
        "Lahore Ravi": "2009\u20132013",
        "Lahore Shalimar": "2009\u20132011",
        "Lahore Eagles": "2010\u20132011",
        "Lahore Lions": "2012\u20132015"
    },
    "birth_date": "1989-7-18",
    "medaltemplates": [
        "Sport: Men's Cricket",
        "Country: {{PAK}}",
        "Competition: South Asian Games",
        "Bronze Medal: 2010 Dhaka Team"
    ]
}