{
    "name": "Iftikhar Ahmed",
    "birth_place": "Kanganpur, Punjab, Pakistan",
    "batting": "Right-handed",
    "source": "http://www.pcboard.com.pk/Pakistan/Players/320/320428/320428.html PCB ",
    "FC": {
        "matches": "9",
        "runs": "303",
        "bat avg": "17.82",
        "100s/50s": "\u2013/1",
        "top score": "52",
        "catches/stumpings": "3/\u2013"
    },
    "LA": {
        "matches": "3",
        "runs": "122",
        "bat avg": "40.66",
        "100s/50s": "\u2013/1",
        "top score": "88",
        "catches/stumpings": "1/\u2013"
    },
    "clubs": {
        "Faisalabad": "2014\u201317"
    },
    "birth_date": "1984-12-14"
}