{
    "name": "Jack Dunning",
    "honorific_suffix": "country=NZL",
    "birth_place": "Omaha, New Zealand",
    "death_date": "1971",
    "death_place": "Adelaide, South Australia",
    "internationalspan": "1933\u20131937",
    "country": "New Zealand",
    "testdebutagainst": "England",
    "testdebutdate": "31 March",
    "testdebutyear": "1933",
    "testcap": "26",
    "lasttestdate": "14 August",
    "lasttestagainst": "England",
    "lasttestyear": "1937",
    "batting": "Right-handed",
    "bowling": "Right-arm Right-arm off-break",
    "source": "http://www.espncricinfo.com/newzealand/content/player/36842.html Cricinfo ",
    "Test": {
        "matches": "4",
        "runs": "38",
        "bat avg": "7.59",
        "100s/50s": "0/0",
        "top score": "19",
        "deliveries": "830",
        "wickets": "5",
        "bowl avg": "98.59",
        "fivefor": "0",
        "tenfor": "0",
        "best bowling": "2/35",
        "catches/stumpings": "2/\u2013"
    },
    "First-class": {
        "matches": "60",
        "runs": "1,057",
        "bat avg": "13.04",
        "100s/50s": "0/0",
        "top score": "45",
        "deliveries": "15,379",
        "wickets": "228",
        "bowl avg": "27.58",
        "fivefor": "15",
        "tenfor": "2",
        "best bowling": "6/42",
        "catches/stumpings": "34/\u2013"
    },
    "clubs": {},
    "birth_date": "1903-2-6"
}