{
    "name": "Jack Durston",
    "batting": "Right-handed",
    "bowling": "Right-arm fast, Right-arm fast, off-break",
    "country": "England",
    "testdebutdate": "11 June",
    "testdebutyear": "1921",
    "lasttestdate": "11 June",
    "lasttestyear": "1921",
    "source": "http://www.espncricinfo.com/england/content/player/11963.html Cricinfo",
    "module": "embed = y",
    "header-color": "#b0c4de |position            = Goalkeeper |youthyears1= |youthclubs1= |years1              = 1912 |clubs1              = Bedford Town |caps1               = 5 |goals1              = 0 |years2              = |clubs2              = Royal Engineers |caps2               = |goals2              = |years3              = |clubs3              = Queens Park Rangers |caps3               = |goals3              = |years4              = 1919\u20131921 |clubs4              = Brentford |caps4               = 44 |goals4              = 0 |years5              = |clubs5              = Northfleet United |caps5               = |goals5              =  ",
    "Tests": {
        "matches": "1",
        "runs": "8",
        "bat avg": "8.00",
        "100s/50s": "-/-",
        "deliveries": "202",
        "wickets": "5",
        "bowl avg": "27.19",
        "fivefor": "\u2013",
        "tenfor": "\u2013",
        "best bowling": "4/102",
        "catches/stumpings": "-/-"
    },
    "First-class": {
        "matches": "386",
        "runs": "3918",
        "bat avg": "11.90",
        "100s/50s": "-/6",
        "deliveries": "72124",
        "wickets": "1329",
        "bowl avg": "22.03",
        "fivefor": "72",
        "tenfor": "11",
        "best bowling": "8/27",
        "catches/stumpings": "257/-"
    },
    "clubs": {}
}