{
    "name": "James Moses",
    "country": "Botswana",
    "fullname": "James Walton Nathaniel Moses",
    "birth_place": "Antigua, Antigua and Barbuda",
    "batting": "Right-handed",
    "T20Idebutdate": "20 May",
    "T20Idebutyear": "2019",
    "T20Idebutagainst": "Uganda",
    "T20Icap": "6",
    "lastT20Idate": "7 November",
    "lastT20Iyear": "2021",
    "lastT20Iagainst": "Tanzania",
    "source": "http://www.espncricinfo.com/ci/content/player/351939.html Cricinfo |bowling=Right-arm Medium",
    "T20I": {
        "matches": "7",
        "runs": "45",
        "bat avg": "7.50",
        "100s/50s": "0/0",
        "top score": "20",
        "deliveries": "48",
        "wickets": "0",
        "bowl avg": "\u2013",
        "fivefor": "\u2013",
        "tenfor": "\u2013",
        "best bowling": "\u2013",
        "catches/stumpings": "2/\u2013"
    },
    "clubs": {},
    "birth_date": "1965-8-8"
}