{
    "name": "Jeff Wilson",
    "honorific_suffix": "country=NZL",
    "birth_name": "Jeffrey William Wilson",
    "birth_place": "Invercargill, New Zealand",
    "spouse": "Adine Harper",
    "school": "Cargill High School",
    "height": "1.80",
    "weight": "94",
    "ru_position": "Wing; Fullback",
    "allblackid": "973",
    "allblackno": "935",
    "ru_nationalteam": "New Zealand",
    "ru_nationalyears": "1993\u20132001",
    "ru_nationalcaps": "60",
    "ru_nationalpoints": "(234)",
    "super14": "Highlanders",
    "super14years": "1996\u20132002",
    "super14caps": "72",
    "super14points": "(175)",
    "ru_province": "Otago, Southland",
    "ru_provinceyears": "1993\u20132002, 1992",
    "ru_provincecaps": "56, 7",
    "ru_provincepoints": "(410), (20)",
    "module": "Infobox cricketer",
    "embed": "yes",
    "country": "New Zealand",
    "batting": "Right-handed",
    "bowling": "Right-arm Right-arm fast-medium",
    "internationalspan": "1993-2005",
    "odidebutdate": "19 March",
    "odidebutyear": "1993",
    "odidebutagainst": "Australia",
    "odicap": "76",
    "lastodidate": "1 March",
    "lastodiyear": "2005",
    "lastodiagainst": "Australia",
    "odishirt": "6",
    "oneT20I": "true",
    "T20Idebutdate": "17 February",
    "T20Idebutyear": "2005",
    "T20Idebutagainst": "Australia",
    "T20Icap": "11",
    "source": "http://content-aus.cricinfo.com/newzealand/content/player/38751.html Cricinfo  ",
    "ODI": {
        "matches": "6",
        "runs": "103",
        "bat avg": "20.60",
        "100s/50s": "0/0",
        "deliveries": "242",
        "wickets": "4",
        "bowl avg": "65.00",
        "fivefor": "0",
        "tenfor": "0",
        "best bowling": "2/21",
        "catches/stumpings": "4/\u2013"
    },
    "T20I": {
        "matches": "1",
        "runs": "18",
        "bat avg": "18.00",
        "100s/50s": "0/0",
        "top score": "18",
        "deliveries": "24",
        "wickets": "0",
        "bowl avg": "\u2013",
        "fivefor": "\u2013",
        "tenfor": "\u2013",
        "best bowling": "\u2013",
        "catches/stumpings": "0/\u2013"
    },
    "clubs": {},
    "birth_date": "1973-10-24"
}