{
    "name": "Jimmy Matthews",
    "fullname": "Thomas James Matthews",
    "birth_place": "Mount Gambier, South Australia",
    "death_date": "df=yes",
    "death_place": "Caulfield, Victoria",
    "batting": "Right-handed",
    "bowling": "Legbreak",
    "country": "Australia",
    "testdebutagainst": "England",
    "testdebutdate": "12 January",
    "testdebutyear": "1912",
    "lasttestdate": "19 August",
    "lasttestagainst": "England",
    "lasttestyear": "1912",
    "source": "http://www.espncricinfo.com/australia/content/player/6527.html CricInfo",
    "Test": {
        "matches": "8",
        "runs": "153",
        "bat avg": "17.00",
        "100s/50s": "0/1",
        "top score": "53",
        "deliveries": "1,081",
        "wickets": "16",
        "bowl avg": "26.18",
        "fivefor": "0",
        "tenfor": "0",
        "best bowling": "4/29",
        "catches/stumpings": "7/0"
    },
    "First-class": {
        "matches": "67",
        "runs": "2,149",
        "bat avg": "24.98",
        "100s/50s": "0/14",
        "top score": "93",
        "deliveries": "7,582",
        "wickets": "177",
        "bowl avg": "25.46",
        "fivefor": "8",
        "tenfor": "1",
        "best bowling": "7/46",
        "catches/stumpings": "56/0"
    },
    "clubs": {},
    "birth_date": "1884-4-3"
}