{
    "name": "Liam Buchanan",
    "country": "Australia",
    "fullname": "Liam Buchanan",
    "birth_place": "Lorne, Victoria, Australia",
    "batting": "Right-handed",
    "bowling": "Right-arm fast Right-arm fast medium",
    "family": "Amon Buchanan (brother) Meyrick Buchanan (brother)",
    "type1": "List A",
    "debutdate1": "3 December",
    "debutyear1": "2005",
    "debutfor1": "Victoria",
    "debutagainst1": "South Australia",
    "lastdate1": "18 February",
    "lastyear1": "2006",
    "lastfor1": "Victoria",
    "lastagainst1": "Tasmania",
    "type2": "T20",
    "debutdate2": "6 January",
    "debutyear2": "2006",
    "debutfor2": "Victoria",
    "debutagainst2": "Western Australia",
    "lastdate2": "21 January",
    "lastyear2": "2006",
    "lastfor2": "Victoria",
    "lastagainst2": "New South Wales",
    "source": "https://cricketarchive.com/Archive/Players/10/10017/10017.html CricketArchive ",
    "List A": {
        "matches": "9",
        "runs": "86",
        "bat avg": "14.33",
        "100s/50s": "0/1",
        "top score": "51",
        "catches/stumpings": "4/0"
    },
    "T20": {
        "matches": "3",
        "runs": "86",
        "bat avg": "28.66",
        "100s/50s": "0/0",
        "top score": "47",
        "catches/stumpings": "0/0"
    },
    "clubs": {
        "Victoria": "2005\u20132006"
    },
    "birth_date": "1969-11-22"
}