{
    "country": "England",
    "fullname": "Michael Humphrey Farebrother",
    "birth_place": "Chelsea, London, England",
    "death_date": "df=yes",
    "death_place": "Seaford, Sussex, England",
    "batting": "Right-handed",
    "bowling": "Left-arm Left-arm fast-medium",
    "source": "http://www.espncricinfo.com/england/content/player/12996.html Cricinfo ",
    "First-class": {
        "matches": "1",
        "runs": "1",
        "bat avg": "0.50",
        "100s/50s": "\u2013/\u2013",
        "top score": "1",
        "deliveries": "224",
        "wickets": "4",
        "bowl avg": "32.00",
        "fivefor": "\u2013",
        "tenfor": "\u2013",
        "best bowling": "2/49",
        "catches/stumpings": "2/\u2013"
    },
    "clubs": {
        "Oxford University": "1939"
    }
}