{
    "name": "Philip Snow",
    "country": "Fiji",
    "fullname": "Philip Albert Snow",
    "birth_place": "Leicester, Leicestershire, England",
    "death_date": "2012",
    "death_place": "England, United Kingdom",
    "source": "http://www.cricinfo.com/ci/content/player/24068.html Cricinfo ",
    "First-class": {
        "matches": "5",
        "runs": "121",
        "bat avg": "17.28",
        "100s/50s": "&ndash;/&ndash;",
        "top score": "38",
        "deliveries": "143",
        "wickets": "4",
        "bowl avg": "25.25",
        "fivefor": "&ndash;",
        "tenfor": "&ndash;",
        "best bowling": "2/60",
        "catches/stumpings": "1/&ndash;"
    },
    "clubs": {},
    "birth_date": "1915-8-7"
}