{
    "country": "England",
    "fullname": "Richard Bladworth Hawkey",
    "birth_place": "Teddington, Middlesex, England",
    "death_date": "df=yes",
    "death_place": "Hillingdon, Middlesex, England",
    "batting": "Right-handed",
    "bowling": "Right-arm Right-arm medium",
    "source": "http://www.espncricinfo.com/england/content/player/14630.html Cricinfo ",
    "First-class": {
        "matches": "3",
        "runs": "42",
        "bat avg": "7.00",
        "100s/50s": "\u2013/\u2013",
        "top score": "13",
        "deliveries": "288",
        "wickets": "1",
        "bowl avg": "139.00",
        "fivefor": "\u2013",
        "tenfor": "\u2013",
        "best bowling": "1/40",
        "catches/stumpings": "-/-"
    },
    "clubs": {}
}