{
    "country": "Namibia",
    "fullname": "Robert Jacobus Herridge",
    "birth_place": "Outjo, Kunene,, South West Africa",
    "heightft": "5",
    "heightinch": "10",
    "batting": "Right-handed",
    "bowling": "Right-arm Right-arm medium",
    "source": "http://www.espncricinfo.com/ci/content/player/830021.html Cricinfo ",
    "First-class": {
        "matches": "2",
        "runs": "0",
        "bat avg": "0.00",
        "100s/50s": "\u2013/\u2013",
        "top score": "0",
        "deliveries": "156",
        "wickets": "1",
        "bowl avg": "115.00",
        "fivefor": "\u2013",
        "tenfor": "\u2013",
        "best bowling": "1/76",
        "catches/stumpings": "1/\u2013"
    },
    "clubs": {
        "Namibia": "2014/15&ndash;2015/16"
    },
    "birth_date": "1989-5-12"
}