{
    "country": "England",
    "fullname": "Robert David Hughes",
    "birth_place": "Rugby, Warwickshire, England",
    "batting": "Left-handed",
    "source": "http://www.espncricinfo.com/ci/content/player/14299.html Cricinfo ",
    "LA": {
        "matches": "7",
        "runs": "78",
        "bat avg": "13.00",
        "100s/50s": "&ndash;/&ndash;",
        "top score": "39",
        "deliveries": "&ndash;",
        "wickets": "&ndash;",
        "bowl avg": "&ndash;",
        "fivefor": "&ndash;",
        "tenfor": "&ndash;",
        "best bowling": "&ndash;",
        "catches/stumpings": "1/&ndash;"
    },
    "clubs": {
        "Herefordshire": "1998-2004"
    },
    "birth_date": "1973-10-26"
}