{
    "name": "Sadu Shinde",
    "full_name": "Sadashiv Ganpatrao Shinde",
    "birth_place": "Bombay, Bombay Presidency, British India",
    "death_date": "1955",
    "death_place": "Bombay, Maharashtra, India",
    "batting": "Right-handed",
    "bowling": "Legbreak Legbreak googly",
    "country": "India",
    "testdebutagainst": "England",
    "testcap": "33",
    "testdebutdate": "22 June",
    "testdebutyear": "1946",
    "lasttestdate": "19 June",
    "lasttestagainst": "England",
    "lasttestyear": "1952",
    "source": "http://content-aus.cricinfo.com/ci/content/player/33999.html CricInfo",
    "Test": {
        "matches": "7",
        "runs": "85",
        "bat avg": "14.16",
        "100s/50s": "0/0",
        "top score": "14",
        "deliveries": "1,515",
        "wickets": "12",
        "bowl avg": "59.75",
        "fivefor": "1",
        "tenfor": "0",
        "best bowling": "6/91",
        "catches/stumpings": "0/\u2013"
    },
    "First-class": {
        "matches": "79",
        "runs": "871",
        "bat avg": "14.04",
        "100s/50s": "0/1",
        "deliveries": "14,961",
        "wickets": "230",
        "bowl avg": "32.59",
        "fivefor": "12",
        "tenfor": "0",
        "best bowling": "8/162",
        "catches/stumpings": "16/\u2013"
    },
    "clubs": {},
    "birth_date": "1923-8-18"
}